argilla-2.7.0.dist-info/METADATA
argilla-2.7.0.dist-info/WHEEL
argilla-2.7.0.dist-info/entry_points.txt
argilla-2.7.0.dist-info/licenses/LICENSE
argilla-2.7.0.dist-info/licenses/LICENSE_HEADER
argilla/__init__.py
argilla/_api/__init__.py
argilla/_api/_base.py
argilla/_api/_client.py
argilla/_api/_datasets.py
argilla/_api/_fields.py
argilla/_api/_http/__init__.py
argilla/_api/_http/_client.py
argilla/_api/_http/_helpers.py
argilla/_api/_metadata.py
argilla/_api/_questions.py
argilla/_api/_records.py
argilla/_api/_token.py
argilla/_api/_users.py
argilla/_api/_vectors.py
argilla/_api/_webhooks.py
argilla/_api/_workspaces.py
argilla/_constants.py
argilla/_exceptions/__init__.py
argilla/_exceptions/_api.py
argilla/_exceptions/_base.py
argilla/_exceptions/_client.py
argilla/_exceptions/_hub.py
argilla/_exceptions/_metadata.py
argilla/_exceptions/_records.py
argilla/_exceptions/_responses.py
argilla/_exceptions/_serialization.py
argilla/_exceptions/_settings.py
argilla/_exceptions/_suggestions.py
argilla/_helpers/__init__.py
argilla/_helpers/_dataclasses.py
argilla/_helpers/_deploy.py
argilla/_helpers/_iterator.py
argilla/_helpers/_log.py
argilla/_helpers/_media.py
argilla/_helpers/_resource_repr.py
argilla/_helpers/_uuid.py
argilla/_models/__init__.py
argilla/_models/_base.py
argilla/_models/_dataset.py
argilla/_models/_dataset_progress.py
argilla/_models/_record/__init__.py
argilla/_models/_record/_metadata.py
argilla/_models/_record/_record.py
argilla/_models/_record/_response.py
argilla/_models/_record/_suggestion.py
argilla/_models/_record/_vector.py
argilla/_models/_resource.py
argilla/_models/_search.py
argilla/_models/_settings/__init__.py
argilla/_models/_settings/_fields.py
argilla/_models/_settings/_metadata.py
argilla/_models/_settings/_questions.py
argilla/_models/_settings/_task_distribution.py
argilla/_models/_settings/_vectors.py
argilla/_models/_user.py
argilla/_models/_webhook.py
argilla/_models/_workspace.py
argilla/_resource.py
argilla/_version.py
argilla/client.py
argilla/datasets/__init__.py
argilla/datasets/_io/__init__.py
argilla/datasets/_io/_disk.py
argilla/datasets/_io/_hub.py
argilla/datasets/_io/card/__init__.py
argilla-2.7.0.dist-info/RECORD
