Metadata-Version: 2.1
Name: argilla
Version: 2.7.0
Summary: The Argilla python server SDK
Author-Email: Argilla <contact@argilla.io>
License: Apache 2.0
Requires-Python: >=3.9
Requires-Dist: httpx>=0.26.0
Requires-Dist: pydantic<3.0.0,>=2.6.0
Requires-Dist: huggingface_hub>=0.22.0
Requires-Dist: tqdm>=4.60.0
Requires-Dist: rich>=10.0.0
Requires-Dist: datasets>=2.0.0
Requires-Dist: pillow>=9.5.0
Requires-Dist: standardwebhooks>=1.0.0
